Workbook

Sheet 匹配指标配置
A1: 参考指标影响系数（0-10） | B1: 指标ID | C1: 指标名称 | D1: 视角 | E1: 类别 | F1: 启用 | G1: 计算方法 | H1: 缺失值策略 | I1: 指标说明 | J1: 候选人输入字段 | K1: 岗位输入字段
A2: 10 | B2: required_skill_coverage | C2: 必需技能覆盖 | D2: recruiter | E2: 技能能力 | F2: TRUE | G2: 字段归一化为0-100分；按A列系数在当前视角内动态归一加权 | H2: exclude | I2: 核验必需技能的精确、可迁移或缺失状态。 | J2: skills | K2: required_skills
A3: 6 | B3: preferred_skill_coverage | C3: 加分技能覆盖 | D3: recruiter | E3: 技能能力 | F3: TRUE | G3: 字段归一化为0-100分；按A列系数在当前视角内动态归一加权 | H3: exclude | I3: 加分技能覆盖：仅依据已提供、与岗位相关且可核验的信息计算；缺失时标记unknown。 | J3: skills | K3: preferred_skills
A4: 8 | B4: skill_proficiency | C4: 技能熟练度 | D4: recruiter | E4: 技能能力 | F4: TRUE | G4: 字段归一化为0-100分；按A列系数在当前视角内动态归一加权 | H4: exclude | I4: 技能熟练度：仅依据已提供、与岗位相关且可核验的信息计算；缺失时标记unknown。 | J4: skills.level | K4: required_skills.level;preferred_skills.level
A5: 7 | B5: skill_experience_years | C5: 技能使用年限 | D5: recruiter | E5: 技能能力 | F5: TRUE | G5: 字段归一化为0-100分；按A列系数在当前视角内动态归一加权 | H5: exclude | I5: 技能使用年限：仅依据已提供、与岗位相关且可核验的信息计算；缺失时标记unknown。 | J5: skills.years | K5: required_skills.years;preferred_skills.years
A6: 6 | B6: skill_recency | C6: 技能近期使用度 | D6: recruiter | E6: 技能能力 | F6: TRUE | G6: 字段归一化为0-100分；按A列系数在当前视角内动态归一加权 | H6: exclude | I6: 技能近期使用度：仅依据已提供、与岗位相关且可核验的信息计算；缺失时标记unknown。 | J6: skills.last_used_year | K6: required_skills;preferred_skills
A7: 8 | B7: evidence_strength | C7: 技能证据强度 | D7: recruiter | E7: 证据成果 | F7: TRUE | G7: 字段归一化为0-100分；按A列系数在当前视角内动态归一加权 | H7: exclude | I7: 技能证据强度：仅依据已提供、与岗位相关且可核验的信息计算；缺失时标记unknown。 | J7: skills.evidence | K7: required_skills;preferred_skills
A8: 7 | B8: quantified_impact | C8: 量化成果强度 | D8: recruiter | E8: 证据成果 | F8: TRUE | G8: 字段归一化为0-100分；按A列系数在当前视角内动态归一加权 | H8: exclude | I8: 量化成果强度：仅依据已提供、与岗位相关且可核验的信息计算；缺失时标记unknown。 | J8: skills.evidence | K8: required_skills;preferred_skills
A9: 9 | B9: responsibility_overlap | C9: 职责证据重合 | D9: recruiter | E9: 岗位履历 | F9: TRUE | G9: 字段归一化为0-100分；按A列系数在当前视角内动态归一加权 | H9: exclude | I9: 职责证据重合：仅依据已提供、与岗位相关且可核验的信息计算；缺失时标记unknown。 | J9: summary;experiences;skills.evidence | K9: responsibilities
A10: 8 | B10: total_experience | C10: 总经验年限 | D10: recruiter | E10: 岗位履历 | F10: TRUE | G10: 字段归一化为0-100分；按A列系数在当前视角内动态归一加权 | H10: exclude | I10: 总经验年限：仅依据已提供、与岗位相关且可核验的信息计算；缺失时标记unknown。 | J10: experience_years | K10: min_experience_years
A11: 6 | B11: industry_experience | C11: 行业经验 | D11: recruiter | E11: 岗位履历 | F11: TRUE | G11: 字段归一化为0-100分；按A列系数在当前视角内动态归一加权 | H11: exclude | I11: 行业经验：仅依据已提供、与岗位相关且可核验的信息计算；缺失时标记unknown。 | J11: industries;industry_experience | K11: industries
A12: 6 | B12: seniority_alignment | C12: 当前职级适配 | D12: recruiter | E12: 岗位履历 | F12: TRUE | G12: 字段归一化为0-100分；按A列系数在当前视角内动态归一加权 | H12: exclude | I12: 当前职级适配：仅依据已提供、与岗位相关且可核验的信息计算；缺失时标记unknown。 | J12: current_seniority | K12: seniority
A13: 5 | B13: project_complexity | C13: 项目复杂度 | D13: recruiter | E13: 岗位履历 | F13: TRUE | G13: 字段归一化为0-100分；按A列系数在当前视角内动态归一加权 | H13: exclude | I13: 项目复杂度：仅依据已提供、与岗位相关且可核验的信息计算；缺失时标记unknown。 | J13: project_complexity | K13: project_complexity_required
... A83: 3.5 | B83: overall_candidate | C83: 求职者侧合成系数 | D83: overall | E83: 双向合成 | F83: TRUE | G83: 企业侧与求职者侧分数的加权调和平均 | H83: required | I83: 控制求职者侧得分在综合分中的影响。 | J83: 404 | K83: 404

Sheet 指标分析
A1: TalentLens 80项匹配指标｜结构与权重模板检查
A4: 核心校验 | B4: 当前值
A5: 匹配指标数 | B5: =COUNTIF(匹配指标配置!$D$2:$D$83,"<>overall") -> 80
A6: 企业侧指标数 | B6: =COUNTIF(匹配指标配置!$D$2:$D$83,"recruiter") -> 42
A7: 求职者侧指标数 | B7: =COUNTIF(匹配指标配置!$D$2:$D$83,"candidate") -> 38
A8: 系数越界数 | B8: =COUNTIF(匹配指标配置!$A$2:$A$83,">10")+COUNTIF(匹配指标配置!$A$2:$A$83,"<0") -> 0
A9: 岗位权重模板数 | B9: =4 -> 4
A11: 类别 | B11: 指标数量 | C11: 系数合计
A12: 协作领导 | B12: =COUNTIF(匹配指标配置!$E$2:$E$83,A12) -> 4 | C12: =SUMIF(匹配指标配置!$E$2:$E$83,A12,匹配指标配置!$A$2:$A$83) -> 24
A13: 发展潜力 | B13: =COUNTIF(匹配指标配置!$E$2:$E$83,A13) -> 2 | C13: =SUMIF(匹配指标配置!$E$2:$E$83,A13,匹配指标配置!$A$2:$A$83) -> 12
A14: 回报福利 | B14: =COUNTIF(匹配指标配置!$E$2:$E$83,A14) -> 5 | C14: =SUMIF(匹配指标配置!$E$2:$E$83,A14,匹配指标配置!$A$2:$A$83) -> 30
A15: 岗位履历 | B15: =COUNTIF(匹配指标配置!$E$2:$E$83,A15) -> 6 | C15: =SUMIF(匹配指标配置!$E$2:$E$83,A15,匹配指标配置!$A$2:$A$83) -> 40
A16: 岗位方向 | B16: =COUNTIF(匹配指标配置!$E$2:$E$83,A16) -> 5 | C16: =SUMIF(匹配指标配置!$E$2:$E$83,A16,匹配指标配置!$A$2:$A$83) -> 34
A17: 工作体验 | B17: =COUNTIF(匹配指标配置!$E$2:$E$83,A17) -> 5 | C17: =SUMIF(匹配指标配置!$E$2:$E$83,A17,匹配指标配置!$A$2:$A$83) -> 28
A18: 工作安排 | B18: =COUNTIF(匹配指标配置!$E$2:$E$83,A18) -> 10 | C18: =SUMIF(匹配指标配置!$E$2:$E$83,A18,匹配指标配置!$A$2:$A$83) -> 56
A19: 工作约束 | B19: =COUNTIF(匹配指标配置!$E$2:$E$83,A19) -> 4 | C19: =SUMIF(匹配指标配置!$E$2:$E$83,A19,匹配指标配置!$A$2:$A$83) -> 20
A20: 成长发展 | B20: =COUNTIF(匹配指标配置!$E$2:$E$83,A20) -> 6 | C20: =SUMIF(匹配指标配置!$E$2:$E$83,A20,匹配指标配置!$A$2:$A$83) -> 38
A21: 技能能力 | B21: =COUNTIF(匹配指标配置!$E$2:$E$83,A21) -> 9 | C21: =SUMIF(匹配指标配置!$E$2:$E$83,A21,匹配指标配置!$A$2:$A$83) -> 61
A22: 文化价值 | B22: =COUNTIF(匹配指标配置!$E$2:$E$83,A22) -> 7 | C22: =SUMIF(匹配指标配置!$E$2:$E$83,A22,匹配指标配置!$A$2:$A$83) -> 47
A23: 行为能力 | B23: =COUNTIF(匹配指标配置!$E$2:$E$83,A23) -> 8 | C23: =SUMIF(匹配指标配置!$E$2:$E$83,A23,匹配指标配置!$A$2:$A$83) -> 48
... A26: 风险合规 | B26: =COUNTIF(匹配指标配置!$E$2:$E$83,A26) -> 1 | C26: =SUMIF(匹配指标配置!$E$2:$E$83,A26,匹配指标配置!$A$2:$A$83) -> 5
A29: 基础判断标准：修改“匹配指标配置”第一列，范围0–10。
A30: 岗位模板：在“岗位权重模板”中修改覆盖系数；未列出的指标继续使用基础系数。
A31: 调用时选择 general、software_engineering、product_operations 或 sales_customer；下一次请求会重新读取工作簿。

Sheet 岗位权重模板
A1: 模板ID | B1: 模板名称 | C1: 版本 | D1: 适用岗位关键词 | E1: 指标ID（留空表示模板元数据） | F1: 覆盖系数（0-10） | G1: 调整理由 | H1: 基础系数（自动） | I1: 变化（自动）
A2: general | B2: 通用岗位 | C2: 1.0 | D2: 全部岗位；未命中的指标沿用基础系数 | G2: 默认模板，不覆盖基础系数 | H2: =IF(E2="","",IFERROR(INDEX(匹配指标配置!$A$2:$A$83,MATCH(E2,匹配指标配置!$B$2:$B$83,0)),"")) | I2: =IF(OR(F2="",H2=""),"",F2-H2)
A3: software_engineering | B3: 软件工程 | C3: 1.0 | D3: 软件、后端、前端、客户端、测试、算法、数据工程 | E3: required_skill_coverage | F3: 10 | G3: 核心技术要求应完整覆盖 | H3: =IF(E3="","",IFERROR(INDEX(匹配指标配置!$A$2:$A$83,MATCH(E3,匹配指标配置!$B$2:$B$83,0)),"")) -> 10 | I3: =IF(OR(F3="",H3=""),"",F3-H3) -> 0
A4: software_engineering | B4: 软件工程 | C4: 1.0 | D4: 软件、后端、前端、客户端、测试、算法、数据工程 | E4: skill_proficiency | F4: 9.5 | G4: 提高核心技能深度的区分度 | H4: =IF(E4="","",IFERROR(INDEX(匹配指标配置!$A$2:$A$83,MATCH(E4,匹配指标配置!$B$2:$B$83,0)),"")) -> 8 | I4: =IF(OR(F4="",H4=""),"",F4-H4) -> 1.5
A5: software_engineering | B5: 软件工程 | C5: 1.0 | D5: 软件、后端、前端、客户端、测试、算法、数据工程 | E5: skill_experience_years | F5: 8.5 | G5: 重视可持续使用经验 | H5: =IF(E5="","",IFERROR(INDEX(匹配指标配置!$A$2:$A$83,MATCH(E5,匹配指标配置!$B$2:$B$83,0)),"")) -> 7 | I5: =IF(OR(F5="",H5=""),"",F5-H5) -> 1.5
A6: software_engineering | B6: 软件工程 | C6: 1.0 | D6: 软件、后端、前端、客户端、测试、算法、数据工程 | E6: evidence_strength | F6: 9 | G6: 代码、项目与交付证据优先 | H6: =IF(E6="","",IFERROR(INDEX(匹配指标配置!$A$2:$A$83,MATCH(E6,匹配指标配置!$B$2:$B$83,0)),"")) -> 8 | I6: =IF(OR(F6="",H6=""),"",F6-H6) -> 1
A7: software_engineering | B7: 软件工程 | C7: 1.0 | D7: 软件、后端、前端、客户端、测试、算法、数据工程 | E7: responsibility_overlap | F7: 9.5 | G7: 技能需服务于实际职责 | H7: =IF(E7="","",IFERROR(INDEX(匹配指标配置!$A$2:$A$83,MATCH(E7,匹配指标配置!$B$2:$B$83,0)),"")) -> 9 | I7: =IF(OR(F7="",H7=""),"",F7-H7) -> 0.5
A8: software_engineering | B8: 软件工程 | C8: 1.0 | D8: 软件、后端、前端、客户端、测试、算法、数据工程 | E8: toolchain_compatibility | F8: 8.5 | G8: 工具链影响上手速度 | H8: =IF(E8="","",IFERROR(INDEX(匹配指标配置!$A$2:$A$83,MATCH(E8,匹配指标配置!$B$2:$B$83,0)),"")) -> 5 | I8: =IF(OR(F8="",H8=""),"",F8-H8) -> 3.5
A9: software_engineering | B9: 软件工程 | C9: 1.0 | D9: 软件、后端、前端、客户端、测试、算法、数据工程 | E9: problem_solving_evidence | F9: 9 | G9: 复杂问题定位与解决是关键行为 | H9: =IF(E9="","",IFERROR(INDEX(匹配指标配置!$A$2:$A$83,MATCH(E9,匹配指标配置!$B$2:$B$83,0)),"")) -> 7 | I9: =IF(OR(F9="",H9=""),"",F9-H9) -> 2
A10: software_engineering | B10: 软件工程 | C10: 1.0 | D10: 软件、后端、前端、客户端、测试、算法、数据工程 | E10: delivery_reliability | F10: 8.5 | G10: 关注工程交付稳定性 | H10: =IF(E10="","",IFERROR(INDEX(匹配指标配置!$A$2:$A$83,MATCH(E10,匹配指标配置!$B$2:$B$83,0)),"")) -> 7 | I10: =IF(OR(F10="",H10=""),"",F10-H10) -> 1.5
A11: software_engineering | B11: 软件工程 | C11: 1.0 | D11: 软件、后端、前端、客户端、测试、算法、数据工程 | E11: learning_agility | F11: 7.5 | G11: 技术更新要求持续学习 | H11: =IF(E11="","",IFERROR(INDEX(匹配指标配置!$A$2:$A$83,MATCH(E11,匹配指标配置!$B$2:$B$83,0)),"")) -> 6 | I11: =IF(OR(F11="",H11=""),"",F11-H11) -> 1.5
A12: software_engineering | B12: 软件工程 | C12: 1.0 | D12: 软件、后端、前端、客户端、测试、算法、数据工程 | E12: work_mode_preference_alignment | F12: 5 | G12: 保留双向约束但避免盖过核心能力 | H12: =IF(E12="","",IFERROR(INDEX(匹配指标配置!$A$2:$A$83,MATCH(E12,匹配指标配置!$B$2:$B$83,0)),"")) -> 7 | I12: =IF(OR(F12="",H12=""),"",F12-H12) -> -2
A13: product_operations | B13: 产品与运营 | C13: 1.0 | D13: 产品经理、产品运营、用户运营、内容运营、增长运营 | E13: responsibility_overlap | F13: 10 | G13: 岗位职责与真实经历是主线 | H13: =IF(E13="","",IFERROR(INDEX(匹配指标配置!$A$2:$A$83,MATCH(E13,匹配指标配置!$B$2:$B$83,0)),"")) -> 9 | I13: =IF(OR(F13="",H13=""),"",F13-H13) -> 1
A14: product_operations | B14: 产品与运营 | C14: 1.0 | D14: 产品经理、产品运营、用户运营、内容运营、增长运营 | E14: industry_experience | F14: 8 | G14: 业务语境影响判断质量 | H14: =IF(E14="","",IFERROR(INDEX(匹配指标配置!$A$2:$A$83,MATCH(E14,匹配指标配置!$B$2:$B$83,0)),"")) -> 6 | I14: =IF(OR(F14="",H14=""),"",F14-H14) -> 2
... A32: sales_customer | B32: 销售与客户成功 | C32: 1.0 | D32: 销售、商务、渠道、客户成功、售前、客户运营 | E32: target_role_alignment | F32: 9 | G32: 岗位方向与个人目标需一致 | H32: =IF(E32="","",IFERROR(INDEX(匹配指标配置!$A$2:$A$83,MATCH(E32,匹配指标配置!$B$2:$B$83,0)),"")) -> 9 | I32: =IF(OR(F32="",H32=""),"",F32-H32) -> 0
